GeoEL/__init__.py
GeoEL/diagnostics.py
GeoEL/kernels.py
GeoEL/model.py
GeoEL/search.py
GeoEL/select_bandwidth.py
GeoEL/utils.py
GeoEL-0.0.0.dist-info/LICENSE
GeoEL-0.0.0.dist-info/METADATA
GeoEL-0.0.0.dist-info/WHEEL
GeoEL-0.0.0.dist-info/top_level.txt
GeoEL-0.0.0.dist-info/RECORD
