Metadata-Version: 2.1
Name: GeoEL
Version: 0.0.0
Summary: Geographically Weighted EnsembleLearning
Home-page: https://github.com/cbsux/GeoEL
Author: ChiBeiSheng
Author-email: cbs3307821258@qq.com
Classifier: Programming Language :: Python :: 3
Classifier: License :: OSI Approved :: MIT License
Classifier: Operating System :: OS Independent
Requires-Python: >=3.8
License-File: LICENSE
Requires-Dist: libpysal ==4.12.1
Requires-Dist: numpy ==2.2.1
Requires-Dist: pandas ==2.2.3
Requires-Dist: matplotlib ==3.10.0
Requires-Dist: scikit-learn ==1.5.2
Requires-Dist: xgboost ==2.1.3
